streamlit_baseweb/__init__.py
streamlit_baseweb/button/build/asset-manifest.json
streamlit_baseweb/button/build/index.html
streamlit_baseweb/button/build/precache-manifest.b5d74bd96e379274fd2ea14bfa52007c.js
streamlit_baseweb/button/build/service-worker.js
streamlit_baseweb/button/build/static/js/2.c1418e57.chunk.js
streamlit_baseweb/button/build/static/js/2.c1418e57.chunk.js.LICENSE.txt
streamlit_baseweb/button/build/static/js/2.c1418e57.chunk.js.map
streamlit_baseweb/button/build/static/js/main.a61d4437.chunk.js
streamlit_baseweb/button/build/static/js/main.a61d4437.chunk.js.map
streamlit_baseweb/button/build/static/js/runtime-main.6f7b4229.js
streamlit_baseweb/button/build/static/js/runtime-main.6f7b4229.js.map
streamlit_baseweb/modal/build/asset-manifest.json
streamlit_baseweb/modal/build/index.html
streamlit_baseweb/modal/build/precache-manifest.335beef11633fc996a1434855591b164.js
streamlit_baseweb/modal/build/service-worker.js
streamlit_baseweb/modal/build/static/js/2.5aa23a28.chunk.js
streamlit_baseweb/modal/build/static/js/2.5aa23a28.chunk.js.LICENSE.txt
streamlit_baseweb/modal/build/static/js/2.5aa23a28.chunk.js.map
streamlit_baseweb/modal/build/static/js/main.fcdf4979.chunk.js
streamlit_baseweb/modal/build/static/js/main.fcdf4979.chunk.js.map
streamlit_baseweb/modal/build/static/js/runtime-main.6f7b4229.js
streamlit_baseweb/modal/build/static/js/runtime-main.6f7b4229.js.map
streamlit_baseweb-0.1.2.dist-info/LICENSE
streamlit_baseweb-0.1.2.dist-info/METADATA
streamlit_baseweb-0.1.2.dist-info/WHEEL
streamlit_baseweb-0.1.2.dist-info/entry_points.txt
streamlit_baseweb-0.1.2.dist-info/top_level.txt
streamlit_baseweb-0.1.2.dist-info/RECORD
