Metadata-Version: 2.1
Name: streamlit-baseweb
Version: 0.1.2
Summary: A Streamlit implementation of the Base Web library.
Home-page: https://github.com/thomasbs17/streamlit-contributions/baseweb_components
Author: Thomas Bouamoud
Author-email: Thomas Bouamoud <thomas.bouamoud@gmail.com>
License: Copyright (c) 2023 Thomas Bouamoud
Project-URL: Homepage, https://github.com/thomasbs17/streamlit-contributions/tree/master/baseweb_components
Keywords: python,streamlit baseweb,streamlit,baseweb,base-web,base_web,front end
Classifier: Programming Language :: Python
Classifier: Programming Language :: Python :: 3
Requires-Python: >=3.6
License-File: LICENSE
Requires-Dist: streamlit (>=0.63)
Provides-Extra: dev
Requires-Dist: black ; extra == 'dev'
Requires-Dist: bumpver ; extra == 'dev'
Requires-Dist: isort ; extra == 'dev'
Requires-Dist: pip-tools ; extra == 'dev'
Requires-Dist: pytest ; extra == 'dev'
